datafold/__init__.py
datafold/_decorators.py
datafold/_version.py
datafold/appfold/__init__.py
datafold/appfold/edmd.py
datafold/appfold/mpc.py
datafold/appfold/tests/__init__.py
datafold/appfold/tests/test_edmd.py
datafold/appfold/tests/test_kmpc.py
datafold/dynfold/__init__.py
datafold/dynfold/base.py
datafold/dynfold/compose.py
datafold/dynfold/dictlearning.py
datafold/dynfold/dmap.py
datafold/dynfold/dmd.py
datafold/dynfold/dynsystem.py
datafold/dynfold/jsf.py
datafold/dynfold/outofsample.py
datafold/dynfold/transform.py
datafold/dynfold/tests/__init__.py
datafold/dynfold/tests/test_base.py
datafold/dynfold/tests/test_compose.py
datafold/dynfold/tests/test_dmap.py
datafold/dynfold/tests/test_dmd.py
datafold/dynfold/tests/test_helper.py
datafold/dynfold/tests/test_jsf.py
datafold/dynfold/tests/test_outofsample.py
datafold/dynfold/tests/test_roseland.py
datafold/dynfold/tests/test_transform.py
datafold/pcfold/__init__.py
datafold/pcfold/distance.py
datafold/pcfold/eigsolver.py
datafold/pcfold/estimators.py
datafold/pcfold/kernels.py
datafold/pcfold/pointcloud.py
datafold/pcfold/tests/__init__.py
datafold/pcfold/tests/test_distance.py
datafold/pcfold/tests/test_estimators.py
datafold/pcfold/tests/test_kernels.py
datafold/pcfold/tests/test_pcmanifold.py
datafold/pcfold/tests/test_tsc_accessor.py
datafold/pcfold/tests/test_tsc_collection.py
datafold/pcfold/tests/test_tsc_metric.py
datafold/pcfold/tests/test_tsc_plots.py
datafold/pcfold/timeseries/__init__.py
datafold/pcfold/timeseries/accessor.py
datafold/pcfold/timeseries/collection.py
datafold/pcfold/timeseries/metric.py
datafold/utils/__init__.py
datafold/utils/_systems.py
datafold/utils/general.py
datafold/utils/plot.py
datafold-2.0.1.dist-info/LICENSE
datafold-2.0.1.dist-info/LICENSES_bundled
datafold-2.0.1.dist-info/METADATA
datafold-2.0.1.dist-info/WHEEL
datafold-2.0.1.dist-info/top_level.txt
datafold-2.0.1.dist-info/RECORD
