Metadata-Version: 2.1
Name: datafold
Version: 2.0.1
Summary: Operator-theoretic models to identify dynamical systems and parametrize point cloud geometry
Home-page: https://datafold-dev.gitlab.io/datafold
Download-URL: https://pypi.org/project/datafold/
Author: datafold development team
Author-email: d.lehmberg@tum.de
License: MIT
Project-URL: Bug Tracker, https://gitlab.com/datafold-dev/datafold/-/issues
Project-URL: Documentation, https://datafold-dev.gitlab.io/datafold/
Project-URL: Source Code, https://gitlab.com/datafold-dev/datafold
Keywords: mathematics, machine learning, dynamical system, data-driven, time series, regression, forecasting, manifold learning, diffusion map, koopman operator, nonlinear
Classifier: Intended Audience :: Science/Research
Classifier: Intended Audience :: Developers
Classifier: License :: OSI Approved :: MIT License
Classifier: Operating System :: OS Independent
Classifier: Programming Language :: Python :: 3 :: Only
Classifier: Topic :: Scientific/Engineering
Classifier: Topic :: Software Development
Requires-Python: >=3.9
License-File: LICENSE
License-File: LICENSES_bundled
Requires-Dist: findiff==0.10.0
Requires-Dist: matplotlib>=3.2.0
Requires-Dist: numexpr<3.0.0,>=2.8.0
Requires-Dist: numpy<1.27.0,>=1.25.0
Requires-Dist: pandas>=2.0.0
Requires-Dist: scikit-learn~=1.2.1
Requires-Dist: scipy<1.12,>=1.10.0
Requires-Dist: tqdm~=4.66.0
